AGambiaeHCRdesign/AGambiaeHCRdesign.py
AGambiaeHCRdesign/__init__.py
agambiaehcrdesign-0.3.0.dist-info/licenses/LICENSE
agambiaehcrdesign-0.3.0.dist-info/METADATA
agambiaehcrdesign-0.3.0.dist-info/WHEEL
agambiaehcrdesign-0.3.0.dist-info/top_level.txt
agambiaehcrdesign-0.3.0.dist-info/RECORD
