Metadata-Version: 2.4
Name: AGambiaeHCRdesign
Version: 0.3.0
Summary: HCR probe designer for A.Gambiae
Home-page: https://github.com/ctucl/AGambiaeHCRdesign
Author: Chintan Trivedi
Author-email: c.trivedi@ucl.ac.uk
Classifier: Programming Language :: Python :: 3
Classifier: Operating System :: OS Independent
Requires-Python: >=3.6
License-File: LICENSE
Requires-Dist: biopython==1.80
Requires-Dist: pandas
Dynamic: author
Dynamic: author-email
Dynamic: classifier
Dynamic: description
Dynamic: description-content-type
Dynamic: home-page
Dynamic: license-file
Dynamic: requires-dist
Dynamic: requires-python
Dynamic: summary
